llama_index/readers/airbyte_stripe/__init__.py
llama_index/readers/airbyte_stripe/base.py
llama_index_readers_airbyte_stripe-0.4.1.dist-info/METADATA
llama_index_readers_airbyte_stripe-0.4.1.dist-info/WHEEL
llama_index_readers_airbyte_stripe-0.4.1.dist-info/licenses/LICENSE
llama_index_readers_airbyte_stripe-0.4.1.dist-info/RECORD
